xtracto/__init__.py
xtracto/_images.py
xtracto-0.0.7.dist-info/LICENSE.txt
xtracto-0.0.7.dist-info/METADATA
xtracto-0.0.7.dist-info/WHEEL
xtracto-0.0.7.dist-info/top_level.txt
xtracto-0.0.7.dist-info/RECORD
