Metadata-Version: 2.1
Name: xtracto
Version: 0.0.7
Summary: Xtracto is a lightweight web development framework designed to simplify the process of creating dynamic web pages using Python and pypx. 
Author: shashstormer
Project-URL: GitHub, https://github.com/shashstormer/xtracto
Classifier: Development Status :: 4 - Beta
Classifier: Intended Audience :: Developers
Classifier: License :: OSI Approved :: MIT License
Classifier: Programming Language :: Python :: 3
Classifier: Programming Language :: Python :: 3.6
Classifier: Programming Language :: Python :: 3.7
Classifier: Programming Language :: Python :: 3.8
Classifier: Programming Language :: Python :: 3.9
Classifier: Topic :: Software Development :: Libraries
Classifier: Topic :: Database
License-File: LICENSE.txt
Requires-Dist: fastapi
Requires-Dist: uvicorn
Requires-Dist: beautifulsoup4
Requires-Dist: requestez
Requires-Dist: pytailwind
